{"dates":[{"date":"08. april 1940","features":[{"id":"aa00002","header":"Sørlandet"}]},{"date":"09. april 1940","features":[{"id":"aa00003","header":"Østlandet"},{"id":"aa00004","header":"Sørlandet"},{"id":"aa00005","header":"Vestlandet"},{"id":"aa00006","header":"Trøndelag"},{"id":"aa00007","header":"Nord-Norge"}]},{"date":"10. april 1940","features":[{"id":"aa00008","header":"Østlandet"},{"id":"aa00009","header":"Sørlandet"},{"id":"aa00010","header":"Vestlandet"},{"id":"aa00011","header":"Trøndelag"},{"id":"aa00012","header":"Nord-Norge"}]},{"date":"11. april 1940","features":[{"id":"aa00013","header":"Østlandet"},{"id":"aa00014","header":"Vestlandet"},{"id":"aa00015","header":"Trøndelag"}]},{"date":"12. april 1940","features":[{"id":"aa00016","header":"Østlandet"},{"id":"aa00017","header":"Trøndelag"}]},{"date":"13. april 1940","features":[{"id":"aa00018","header":"Østlandet"},{"id":"aa00019","header":"Vestlandet"},{"id":"aa00020","header":"Nord-Norge"}]}]}